{
  "updates": [
    {
      "id": "itch-auto-samurai-breed-0f05311",
      "date": "2026-06-01",
      "category": "itch.io自動更新",
      "title": "サムライブリード - 契りノ血脈 -を自動更新しました",
      "body": "ゲーム本体の新しいコミット 0f05311 を検知し、itch.ioへ自動アップロードしました。",
      "url": "https://sengokugekokujobeats.itch.io/samurai-breed",
      "approved": true,
      "discord": true,
      "source": "itch-auto",
      "game": "samurai-breed",
      "commit": "https://github.com/Sengokugekokuzyou/samurai-breed/commit/0f05311d5f3b5b57b83fa82f45597307cf3d0aa9"
    },
    {
      "id": "itch-auto-samurai-cypher-510f1a7",
      "date": "2026-06-01",
      "category": "itch.io自動更新",
      "title": "戦国下剋上BEATS - SAMURAI CYPHER -を自動更新しました",
      "body": "ゲーム本体の新しいコミット 510f1a7 を検知し、itch.ioへ自動アップロードしました。",
      "url": "https://sengokugekokujobeats.itch.io/beats-samurai-cypher",
      "approved": true,
      "discord": true,
      "source": "itch-auto",
      "game": "samurai-cypher",
      "commit": "https://github.com/Sengokugekokuzyou/samurai-cypher/commit/510f1a781b8f8cdc29d8167a9a9906e8ed4b5cfb"
    },
    {
      "id": "youtube-QZT5-TXeS-E",
      "date": "2026-06-01",
      "category": "YouTube",
      "title": "YouTube更新: 【生か死か】片倉小十郎vs佐瀬種常 - 摺上原の決戦 / 独眼竜の刃と不退転の盾｜戦国HIPHOP",
      "body": "新しい動画を公開しました。チャンネル: @戦国下剋上BEATS",
      "url": "https://www.youtube.com/watch?v=QZT5-TXeS-E",
      "approved": true,
      "discord": true,
      "source": "youtube"
    },
    {
      "id": "youtube-ef2oIoyg_AU",
      "date": "2026-05-29",
      "category": "YouTube",
      "title": "YouTube更新: 【比類なき武功】伊達成実 vs 佐竹義重 - 人取橋の一騎当千 / 七千で三万を止めた夜｜戦国HIPHOP",
      "body": "新しい動画を公開しました。チャンネル: @戦国下剋上BEATS",
      "url": "https://www.youtube.com/watch?v=ef2oIoyg_AU",
      "approved": true,
      "discord": true,
      "source": "youtube"
    },
    {
      "id": "youtube-sl4eW7pe0U0",
      "date": "2026-05-28",
      "category": "YouTube",
      "title": "YouTube更新: 【戦国を甘く染めた南蛮の星】金平糖 - 異国の煌めきと信長の夢 ｜戦国HIPHOP",
      "body": "新しい動画を公開しました。チャンネル: @戦国下剋上BEATS",
      "url": "https://www.youtube.com/watch?v=sl4eW7pe0U0",
      "approved": true,
      "discord": true,
      "source": "youtube"
    },
    {
      "id": "youtube-pf11k-ruEn8",
      "date": "2026-05-26",
      "category": "YouTube",
      "title": "YouTube更新: 【三日天下の月夜】明智光秀 ― 裁きの果てに残る影 / Judgment Night｜戦国R&B",
      "body": "新しい動画を公開しました。チャンネル: @戦国下剋上BEATS",
      "url": "https://www.youtube.com/watch?v=pf11k-ruEn8",
      "approved": true,
      "discord": true,
      "source": "youtube"
    },
    {
      "id": "youtube-QJcqpDjbZzc",
      "date": "2026-05-25",
      "category": "YouTube",
      "title": "YouTube更新: 【退くな政宗】伊達成実 - 勇武無双の猛将 / 俺が死ぬまでお前を逃がさない｜戦国HIPHOP",
      "body": "新しい動画を公開しました。チャンネル: @戦国下剋上BEATS",
      "url": "https://www.youtube.com/watch?v=QJcqpDjbZzc",
      "approved": true,
      "discord": true,
      "source": "youtube"
    },
    {
      "id": "youtube-GoReESsl6Jo",
      "date": "2026-05-23",
      "category": "YouTube",
      "title": "YouTube更新: 【撃ってくれ】鬼庭良直 vs 岩城常隆 - 人取橋の死闘 / 七十三の老将が政宗の盾になった｜戦国HIPHOP",
      "body": "新しい動画を公開しました。チャンネル: @戦国下剋上BEATS",
      "url": "https://www.youtube.com/watch?v=GoReESsl6Jo",
      "approved": true,
      "discord": true,
      "source": "youtube"
    },
    {
      "id": "2026-06-01-discord-channel-test-0115",
      "date": "2026-06-01",
      "category": "Discord接続テスト",
      "title": "更新情報チャンネルへの自動投稿テストです",
      "body": "Webhookの投稿先を更新情報チャンネルへ差し替えた後の確認投稿です。ここに表示されれば完成です。",
      "url": "https://sengokugekokuzyou.github.io/",
      "approved": true,
      "discord": true
    },
    {
      "id": "2026-06-01-discord-test-0110",
      "date": "2026-06-01",
      "category": "Discord接続テスト",
      "title": "Discord自動投稿の再テストです",
      "body": "ワークフローのエラーを修正しました。この投稿が表示されれば接続成功です。",
      "url": "https://sengokugekokuzyou.github.io/",
      "approved": true,
      "discord": true
    },
    {
      "id": "2026-06-01-discord-test-0106",
      "date": "2026-06-01",
      "category": "Discord接続テスト",
      "title": "Discord自動投稿の接続テストです",
      "body": "この投稿が更新情報チャンネルに表示されれば、公式HPからDiscordへの自動発信が成功しています。",
      "url": "https://sengokugekokuzyou.github.io/",
      "approved": true,
      "discord": true
    },
    {
      "id": "2026-06-01-automation-ready",
      "date": "2026-06-01",
      "category": "運用自動化",
      "title": "更新情報の自動発信設定が完了しました",
      "body": "公式HP、Discord、YouTube新着検知をつなぐ更新情報の自動反映フローを設定しました。",
      "url": "https://sengokugekokuzyou.github.io/",
      "approved": true,
      "discord": true
    },
    {
      "id": "2026-06-01-official-site-open",
      "date": "2026-06-01",
      "category": "公式HP",
      "title": "戦国下剋上BEATS公式HPを公開しました",
      "body": "作品情報、公式Discord、広告収益化準備の情報をまとめる公式HPを公開しました。",
      "url": "https://sengokugekokuzyou.github.io/",
      "approved": true,
      "discord": true
    }
  ]
}
